Workbook

Sheet Hypothèses
A1: GRILLE DE COÛTS — Accord-cadre OPCO 2i, Lot 4, brique vidéo (Pôle Audiovisuel L'Étudiant)
A2: ⚠️ DOCUMENT INTERNE — NE PAS TRANSMETTRE AU CLIENT (grille de coûts, sources et référentiels internes). Cellules jaunes = valeurs modifiables (inputs). Cellules blanches = calculées automatiquement. Chiffrage = coût de revient production (HT). Les OPS y appliquent leur marge commerciale pour fixer le 'Prix plafond HT' réellement déclaré dans le bordereau officiel (onglet BPP), seul document transmis au client.
A3: Poste | B3: Valeur | C3: Unité | D3: Source
A4: Storyboarder (freelance) | B4: 400 | C4: €/j | D4: BPU IDFM Grille Coûts Production — Marché pub
A5: Monteur·se | B5: 500 | C5: €/j | D5: BPU IDFM Grille Coûts Production — COMETES / Malt
A6: Motion designer | B6: 600 | C6: €/j | D6: BPU IDFM Grille Coûts Production — Marché pub / Malt
A7: Cadreur / JRI (image + son, tournage léger 1 lieu) | B7: 550 | C7: €/j | D7: BPU IDFM Grille Coûts Production — COMETES / Malt
A8: Comédien voix off (session) | B8: 450 | C8: € | D8: BPU IDFM Grille Coûts Production — Marché / CCN
A9: Taux interne (supervision / coordination) | B9: 200 | C9: €/j | D9: Référentiel de Coûts Internes Pôle Audiovisuel — validé Direction
A10: Kit tournage léger | B10: 300 | C10: €/j | D10: BPU IDFM Grille Coûts Production
A11: Déplacement forfaitaire (1 lieu, équipe légère, moyenne IDF/province) | B11: 400 | C11: € | D11: Référentiel interne — session CNES/COMETES
A12: Pilotage (% charge de production) | B12: 0.05 | C12: % | D12: BPU IDFM Grille Coûts Production — méthodologie BPU/DQE
A13: Assurance production (projets avec tournage) | B13: 0.03 | C13: % | D13: BPU IDFM Grille Coûts Production
A14: Provision imprévus (projets avec tournage) | B14: 0.05 | C14: % | D14: BPU IDFM Grille Coûts Production
A15: TVA | B15: 0.2 | C15: % | D15: Taux standard
A17: HYPOTHÈSES — CALENDRIER (répartition dans le temps, aucune donnée contractuelle)
A18: Durée totale accord-cadre (hypothèse de répartition) | B18: 41 | C18: mois | D18: Fiche Synthèse AO OPCO2i — 5 mois initiaux + 3 reconductions annuelles

Sheet Coût unitaire - Ligne 8
A1: LIGNE 8 — VIDÉO COURTE VERTICALE 30-60S À PARTIR D'EXISTANT (qté DQE : 25)
A2: Poste | B2: Jours / Quantité | C2: Taux unitaire | D2: Coût
A3: FABRICATION
A4: Montage | B4: 0.5 | C4: =Hypothèses!$B$5 -> 500 | D4: =B4*C4 -> 250
A5: Habillage / motion léger | B5: 0.25 | C5: =Hypothèses!$B$6 -> 600 | D5: =B5*C5 -> 150
A6: Supervision interne | B6: 0.1 | C6: =Hypothèses!$B$9 -> 200 | D6: =B6*C6 -> 20
A7: Sous-total | D7: =SUM(D4:D6) -> 420
A8: Pilotage | C8: =Hypothèses!$B$12 -> 0.05 | D8: =D7*C8 -> 21
A9: COÛT DE REVIENT (HT) — forfait | D9: =D7+D8 -> 441

Sheet Coût unitaire - Ligne 9
A1: LIGNE 9 — VIDÉO ÉDITORIALE 2-4MIN SANS TOURNAGE (qté DQE : 12)
A2: Poste | B2: Jours / Quantité | C2: Taux unitaire | D2: Coût
A3: FABRICATION
A4: Storyboard | B4: 0.75 | C4: =Hypothèses!$B$4 -> 400 | D4: =B4*C4 -> 300
A5: Montage / motion design | B5: 1.5 | C5: =Hypothèses!$B$5 -> 500 | D5: =B5*C5 -> 750
A6: Habillage / motion design | B6: 1 | C6: =Hypothèses!$B$6 -> 600 | D6: =B6*C6 -> 600
A7: Voix off (1 session, si nécessaire) | B7: 1 | C7: =Hypothèses!$B$8 -> 450 | D7: =B7*C7 -> 450
A8: Supervision interne | B8: 0.25 | C8: =Hypothèses!$B$9 -> 200 | D8: =B8*C8 -> 50
A9: Sous-total | D9: =SUM(D4:D8) -> 2150
A10: Pilotage | C10: =Hypothèses!$B$12 -> 0.05 | D10: =D9*C10 -> 107.5
A11: COÛT DE REVIENT (HT) — forfait | D11: =D9+D10 -> 2257.5

Sheet Coût unitaire - Ligne 10
A1: LIGNE 10 — VIDÉO ÉDITORIALE 2-4MIN AVEC TOURNAGE, 1 JOUR/1 LIEU (qté DQE : 10)
A2: Poste | B2: Jours / Quantité | C2: Taux unitaire | D2: Coût
A3: FABRICATION
A4: Préparation (interne) | B4: 0.5 | C4: =Hypothèses!$B$9 -> 200 | D4: =B4*C4 -> 100
A5: Tournage — Cadreur/JRI (image+son) | B5: 1 | C5: =Hypothèses!$B$7 -> 550 | D5: =B5*C5 -> 550
A6: Supervision interne (tournage) | B6: 0.25 | C6: =Hypothèses!$B$9 -> 200 | D6: =B6*C6 -> 50
A7: Kit tournage léger | B7: 1 | C7: =Hypothèses!$B$10 -> 300 | D7: =B7*C7 -> 300
A8: Déplacement forfaitaire | B8: 1 | C8: =Hypothèses!$B$11 -> 400 | D8: =B8*C8 -> 400
A9: Montage | B9: 2 | C9: =Hypothèses!$B$5 -> 500 | D9: =B9*C9 -> 1000
A10: Habillage / motion design | B10: 0.5 | C10: =Hypothèses!$B$6 -> 600 | D10: =B10*C10 -> 300
A11: Déclinaison courte additionnelle | B11: 0.5 | C11: =Hypothèses!$B$5 -> 500 | D11: =B11*C11 -> 250
A12: Sous-total | D12: =SUM(D4:D11) -> 2950
A13: Pilotage | C13: =Hypothèses!$B$12 -> 0.05 | D13: =D12*C13 -> 147.5
A14: Assurance production | C14: =Hypothèses!$B$13 -> 0.03 | D14: =D12*C14 -> 88.5
A15: Provision imprévus | C15: =Hypothèses!$B$14 -> 0.05 | D15: =D12*C15 -> 147.5
A16: COÛT DE REVIENT (HT) — forfait | D16: =D12+D13+D14+D15 -> 3333.5

Sheet Récap pour bordereau
A1: RÉCAP POUR BORDEREAU — Consultation 2026-71, Lot 4 (brique vidéo, lignes 8/9/10)
A2: Ligne du bordereau officiel | B2: Qté DQE (non contractuelle) | C2: Coût de revient HT (forfait) | D2: Total pondéré (coût × qté)
A3: Ligne 8 — Vidéo courte verticale 30-60s à partir d'existant (qté DQE : 25) | B3: 25 | C3: ='Coût unitaire - Ligne 8'!D9 -> 441 | D3: =B3*C3 -> 11025
A4: Ligne 9 — Vidéo éditoriale 2-4min sans tournage (qté DQE : 12) | B4: 12 | C4: ='Coût unitaire - Ligne 9'!D11 -> 2257.5 | D4: =B4*C4 -> 27090
A5: Ligne 10 — Vidéo éditoriale 2-4min avec tournage, 1 jour/1 lieu (qté DQE : 10) | B5: 10 | C5: ='Coût unitaire - Ligne 10'!D16 -> 3333.5 | D5: =B5*C5 -> 33335
A6: TOTAL (volume de vidéos & coût de revient, 3 lignes vidéo) | B6: =SUM(B3:B5) -> 47 | D6: =SUM(D3:D5) -> 71450
A8: Note : quantités DQE indicatives, non contractuelles — volontairement majorées par le client. Le Prix plafond HT à déclarer dans le bordereau officiel (onglet BPP) reste à définir par les OPS, en ajoutant leur marge commerciale à ce coût de revient.

Sheet Volumes dans le temps
A1: RÉPARTITION DANS LE TEMPS — hypothèse (aucun calendrier de commande connu à ce stade)
A2: Période | B2: Durée (mois) | C2: % durée totale | D2: Qté Ligne 8 | E2: Qté Ligne 9 | F2: Qté Ligne 10 | G2: Qté totale (toutes lignes) | H2: Coût de revient total (période)
A3: Période initiale (jusqu'au 31/03/2027) | B3: 5 | C3: =B3/Hypothèses!$B$18 -> 0.12195122 | D3: =$C3*25 -> 3.0487805 | E3: =$C3*12 -> 1.4634146 | F3: =$C3*10 -> 1.2195122 | G3: =D3+E3+F3 -> 5.7317073 | H3: =D3*'Récap pour bordereau'!$C$3+E3*'Récap pour bordereau'!$C$4+F3*'Récap pour bordereau'!$C$5 -> 8713.4146
A4: Reconduction 1 (2027-2028) | B4: 12 | C4: =B4/Hypothèses!$B$18 -> 0.29268293 | D4: =$C4*25 -> 7.3170732 | E4: =$C4*12 -> 3.5121951 | F4: =$C4*10 -> 2.9268293 | G4: =D4+E4+F4 -> 13.756098 | H4: =D4*'Récap pour bordereau'!$C$3+E4*'Récap pour bordereau'!$C$4+F4*'Récap pour bordereau'!$C$5 -> 20912.195
A5: Reconduction 2 (2028-2029) | B5: 12 | C5: =B5/Hypothèses!$B$18 -> 0.29268293 | D5: =$C5*25 -> 7.3170732 | E5: =$C5*12 -> 3.5121951 | F5: =$C5*10 -> 2.9268293 | G5: =D5+E5+F5 -> 13.756098 | H5: =D5*'Récap pour bordereau'!$C$3+E5*'Récap pour bordereau'!$C$4+F5*'Récap pour bordereau'!$C$5 -> 20912.195
A6: Reconduction 3 (2029-2030) | B6: 12 | C6: =B6/Hypothèses!$B$18 -> 0.29268293 | D6: =$C6*25 -> 7.3170732 | E6: =$C6*12 -> 3.5121951 | F6: =$C6*10 -> 2.9268293 | G6: =D6+E6+F6 -> 13.756098 | H6: =D6*'Récap pour bordereau'!$C$3+E6*'Récap pour bordereau'!$C$4+F6*'Récap pour bordereau'!$C$5 -> 20912.195
A7: TOTAL | B7: =SUM(B3:B6) -> 41 | C7: =SUM(C3:C6) -> 1 | D7: =SUM(D3:D6) -> 25 | E7: =SUM(E3:E6) -> 12 | F7: =SUM(F3:F6) -> 10 | G7: =SUM(G3:G6) -> 47 | H7: =SUM(H3:H6) -> 71450
A9: ⚠️ Hypothèse de répartition uniforme sur la durée du contrat — OPCO 2i ne communique aucun calendrier de commande. Les quantités DQE (25/12/10) sont elles-mêmes indicatives et non contractuelles. Ce tableau sert à visualiser un ordre de grandeur de charge par période, pas un engagement de volume.
