Workbook

Sheet Hypothèses
A1: GRILLE DE COÛTS — AO ANFA 2027, Lot 1 vidéos métiers et formations (Pôle Audiovisuel L'Etudiant)
A2: ⚠️ DOCUMENT INTERNE — NE PAS TRANSMETTRE AU CLIENT (coûts de revient, sources et référentiel interne). Cellules bleu sur jaune = valeurs modifiables ; tout le reste recalcule.
A3: Poste | B3: Valeur | C3: Unité | D3: Source
A4: TJM — SCÉNARIO B (repli freelances, tarifs marché — si la bande passante de la cellule est faible)
A5: JRI — cadreur/journaliste reporter d'images (réalise et cadre sur le terrain) | B5: 550 | C5: €/j | D5: BPU IDFM Grille Coûts Production — COMETES / Malt (tarif en vigueur de la grille). Remplace le réalisateur (décision Martin, 28/10)
A6: Ingénieur·e du son / 2e caméra | B6: 500 | C6: €/j | D6: BPU IDFM Grille Coûts Production — COMETES / CCPA
A7: Monteur·se | B7: 500 | C7: €/j | D7: BPU IDFM Grille Coûts Production — COMETES / Malt
A8: Motion designer (habillage Métiers Services Auto) | B8: 600 | C8: €/j | D8: BPU IDFM Grille Coûts Production — Marché pub / Malt
A9: Étalonneur·se | B9: 480 | C9: €/j | D9: BPU IDFM Grille Coûts Production — COMETES / Malt
A10: Mixeur·se | B10: 480 | C10: €/j | D10: BPU IDFM Grille Coûts Production — COMETES / CCPA
A11: TAUX — SCÉNARIO A (base de l'offre : équipe interne de la cellule vidéo)
A12: Taux interne (jour/personne, masse salariale) | B12: 200 | C12: €/j | D12: Référentiel de Coûts Internes Pôle Audiovisuel — validé Direction
A13: Matériel interne (caméras, son, lumière de la cellule) | B13: 0 | C13: €/j | D13: Amortissement exclu du référentiel interne — à valoriser par les OPS si besoin
A14: COMMUN AUX DEUX SCÉNARIOS
A15: Location kit tournage léger (scénario B) | B15: 300 | C15: €/j | D15: BPU IDFM Grille Coûts Production — reportage / ITW
A16: Stockage rushes par vidéo | B16: 50 | C16: € | D16: BPU IDFM Grille Coûts Production
A17: Pilotage (% du sous-total de production) | B17: 0.15 | C17: % | D17: Méthode de pilotage AO — 15 % (relation client à l'année : lancement, calage campagnes ANFA, bilans)
A18: Assurance production | B18: 0.03 | C18: % | D18: BPU IDFM Grille Coûts Production — obligatoire pour tout projet avec tournage
A19: Provision imprévus (météo, retakes, intervenant absent) | B19: 0.05 | C19: % | D19: BPU IDFM Grille Coûts Production — obligatoire pour tout projet avec tournage
A20: TVA | B20: 0.2 | C20: % | D20: Taux standard
A21: LOGISTIQUE D'UNE VAGUE DE TOURNAGE EN RÉGION
A22: Personnes en déplacement | B22: 2 | C22: pers | D22: Équipe légère : JRI + son / 2e caméra (sobriété, critère RSE)
A23: Jours de tournage par vague | B23: 3 | C23: j | D23: Fiche Approche : J1 entreprise (court métier + long), J2 CFA (court formation + long), J3 long
A24: Nuits sur place par vague | B24: 3 | C24: nuits | D24: Arrivée la veille de J1 ; sites potentiellement dans deux villes
A25: Transport A/R Paris–région par personne | B25: 150 | C25: €/pers | D25: Estimation marché — train 2de classe, destination non arrêtée
A26: Nuitée hôtel par personne | B26: 95 | C26: €/nuit/pers | D26: Estimation marché — hôtel pro province (référence CYRCE/BIOT2)
A27: Per diem repas par personne et par jour | B27: 40 | C27: €/j/pers | D27: Barème URSSAF frais professionnels 2026 — base 2 repas/jour (référence CYRCE/BIOT2)
A28: Location véhicule sur place | B28: 70 | C28: €/j | D28: Estimation marché — utilitaire léger / citadine
A29: VOLUMES ET CLÉS DE RÉPARTITION
A30: Nombre de vagues de tournage par an | B30: 2 | C30: vagues | D30: Calendrier 2027 : fin février–mars, puis mai
A31: Formats courts par an (60–120 s) | B31: 4 | C31: vidéos | D31: CDC §3.1 + réponse ANFA du 28/10 : 2 métiers + 2 formations a minima
A32: Formats longs par an (10–15 min) | B32: 2 | C32: vidéos | D32: CDC §3.1 + réponse ANFA du 28/10 : 2 thématiques par an
A33: Part de la logistique d'une vague imputée à chaque court | B33: 0.25 | C33: % | D33: Clé interne : une vague = 2 courts (25 % chacun) + 1 long (50 %)
A34: Part de la logistique d'une vague imputée au long | B34: 0.5 | C34: % | D34: Clé interne — la somme des clés doit faire 100 %
A35: CADRE CLIENT
A36: Budget annuel maximum Lot 1 (HT), production + diffusion | B36: 58000 | C36: € | D36: RC / CDC §4 — accord-cadre sans minimum ; achats médias inclus (réponse ANFA du 28/10)
A37: Repère marge plancher OPS (multiplicateur sur coût de revient) | B37: 1.3 | C37: x | D37: BPU IDFM — Repères de marge (×1,3 plancher, ×1,5 standard secteur public). Décision OPS
A38: Contrôle : somme des clés de répartition d'une vague | B38: =2*B33+B34 -> 1 | D38: Doit afficher 100 %

Sheet Format court
A1: FORMAT COURT — vidéo métier ou formation, 60–120 s, verticale, immersive (4 par an minimum)
A2: Scénario A (base) = équipe interne de la cellule vidéo (taux 200 €/j) · Scénario B (repli) = freelances aux tarifs marché, si la bande passante est faible. Jours en bleu = modifiables.
A3: Poste | B3: Jours / Qté | C3: Taux A | D3: Coût A (interne) | E3: Taux B | F3: Coût B (freelances)
A4: PRÉPARATION
A5: Préparation : brief des intervenants, autorisations droit à l'image (mineurs), feuille de route | B5: 0.5 | C5: =Hypothèses!$B$12 -> 200 | D5: =B5*C5 -> 100 | E5: =Hypothèses!$B$12 -> 200 | F5: =B5*E5 -> 100
A6: TOURNAGE (½ journée, mutualisée avec le format long sur le même site)
A7: JRI (réalise et cadre) | B7: 0.5 | C7: =Hypothèses!$B$12 -> 200 | D7: =B7*C7 -> 100 | E7: =Hypothèses!$B$5 -> 550 | F7: =B7*E7 -> 275
A8: Ingénieur·e du son / 2e caméra | B8: 0.5 | C8: =Hypothèses!$B$12 -> 200 | D8: =B8*C8 -> 100 | E8: =Hypothèses!$B$6 -> 500 | F8: =B8*E8 -> 250
A9: Kit tournage léger | B9: 0.5 | C9: =Hypothèses!$B$13 -> 0 | D9: =B9*C9 -> 0 | E9: =Hypothèses!$B$15 -> 300 | F9: =B9*E9 -> 150
A10: Supervision interne (tournage, relation intervenants) | B10: 0.25 | C10: =Hypothèses!$B$12 -> 200 | D10: =B10*C10 -> 50 | E10: =Hypothèses!$B$12 -> 200 | F10: =B10*E10 -> 50
A11: POST-PRODUCTION
A12: Dérush + montage vertical | B12: 1.5 | C12: =Hypothèses!$B$12 -> 200 | D12: =B12*C12 -> 300 | E12: =Hypothèses!$B$7 -> 500 | F12: =B12*E12 -> 750
A13: Habillage / motion (charte Métiers Services Auto) | B13: 0.5 | C13: =Hypothèses!$B$12 -> 200 | D13: =B13*C13 -> 100 | E13: =Hypothèses!$B$8 -> 600 | F13: =B13*E13 -> 300
A14: Étalonnage | B14: 0.25 | C14: =Hypothèses!$B$12 -> 200 | D14: =B14*C14 -> 50 | E14: =Hypothèses!$B$9 -> 480 | F14: =B14*E14 -> 120
A15: Mix | B15: 0.25 | C15: =Hypothèses!$B$12 -> 200 | D15: =B15*C15 -> 50 | E15: =Hypothèses!$B$10 -> 480 | F15: =B15*E15 -> 120
A16: Sous-titrage (lecture sans le son) | B16: 0.25 | C16: =Hypothèses!$B$12 -> 200 | D16: =B16*C16 -> 50 | E16: =Hypothèses!$B$7 -> 500 | F16: =B16*E16 -> 125
A17: Retours ANFA — 2 allers-retours inclus | B17: 0.5 | C17: =Hypothèses!$B$12 -> 200 | D17: =B17*C17 -> 100 | E17: =Hypothèses!$B$7 -> 500 | F17: =B17*E17 -> 250
A18: Stockage rushes | B18: 1 | C18: =Hypothèses!$B$16 -> 50 | D18: =B18*C18 -> 50 | E18: =Hypothèses!$B$16 -> 50 | F18: =B18*E18 -> 50
A19: Sous-total production | D19: =SUM(D5:D18) -> 1050 | F19: =SUM(F5:F18) -> 2540
A20: Pilotage | C20: =Hypothèses!$B$17 -> 0.15 | D20: =D19*C20 -> 157.5 | E20: =Hypothèses!$B$17 -> 0.15 | F20: =F19*E20 -> 381
A21: Assurance production | C21: =Hypothèses!$B$18 -> 0.03 | D21: =D19*C21 -> 31.5 | E21: =Hypothèses!$B$18 -> 0.03 | F21: =F19*E21 -> 76.2
A22: Provision imprévus | C22: =Hypothèses!$B$19 -> 0.05 | D22: =D19*C22 -> 52.5 | E22: =Hypothèses!$B$19 -> 0.05 | F22: =F19*E22 -> 127
A23: COÛT DE REVIENT PRODUCTION (HT) — par vidéo, hors logistique | D23: =D19+D20+D21+D22 -> 1291.5 | F23: =F19+F20+F21+F22 -> 3124.2
A25: Un court est tourné en une demi-journée, sur le même site et le même jour qu'une partie du format long. La logistique (transport, hôtel, repas) est chiffrée dans l'onglet « Logistique vague » et imputée dans la Synthèse.

Sheet Format long
A1: FORMAT LONG — vidéo thématique, 10–15 min, verticale, immersive, chapitrée (2 par an minimum)
A2: Scénario A (base) = équipe interne de la cellule vidéo (taux 200 €/j) · Scénario B (repli) = freelances aux tarifs marché, si la bande passante est faible. Jours en bleu = modifiables.
A3: Poste | B3: Jours / Qté | C3: Taux A | D3: Coût A (interne) | E3: Taux B | F3: Coût B (freelances)
A4: ÉCRITURE ET PRÉPARATION
A5: Écriture : angle, structure chapitrée, choix des intervenants avec l'ANFA | B5: 1.5 | C5: =Hypothèses!$B$12 -> 200 | D5: =B5*C5 -> 300 | E5: =Hypothèses!$B$5 -> 550 | F5: =B5*E5 -> 825
A6: Préparation : repérages à distance, brief, autorisations droit à l'image | B6: 1 | C6: =Hypothèses!$B$12 -> 200 | D6: =B6*C6 -> 200 | E6: =Hypothèses!$B$12 -> 200 | F6: =B6*E6 -> 200
A7: TOURNAGE (2 jours : ½ j sur chaque site des courts + 1 j dédié)
A8: JRI (réalise et cadre) | B8: 2 | C8: =Hypothèses!$B$12 -> 200 | D8: =B8*C8 -> 400 | E8: =Hypothèses!$B$5 -> 550 | F8: =B8*E8 -> 1100
A9: Ingénieur·e du son / 2e caméra | B9: 2 | C9: =Hypothèses!$B$12 -> 200 | D9: =B9*C9 -> 400 | E9: =Hypothèses!$B$6 -> 500 | F9: =B9*E9 -> 1000
A10: Kit tournage léger | B10: 2 | C10: =Hypothèses!$B$13 -> 0 | D10: =B10*C10 -> 0 | E10: =Hypothèses!$B$15 -> 300 | F10: =B10*E10 -> 600
A11: Supervision interne | B11: 0.5 | C11: =Hypothèses!$B$12 -> 200 | D11: =B11*C11 -> 100 | E11: =Hypothèses!$B$12 -> 200 | F11: =B11*E11 -> 100
A12: POST-PRODUCTION
A13: Dérush | B13: 1.5 | C13: =Hypothèses!$B$12 -> 200 | D13: =B13*C13 -> 300 | E13: =Hypothèses!$B$7 -> 500 | F13: =B13*E13 -> 750
A14: Montage (10–15 min, vertical, chapitré) | B14: 5 | C14: =Hypothèses!$B$12 -> 200 | D14: =B14*C14 -> 1000 | E14: =Hypothèses!$B$7 -> 500 | F14: =B14*E14 -> 2500
A15: Habillage / motion (titres de chapitres, charte) | B15: 1.5 | C15: =Hypothèses!$B$12 -> 200 | D15: =B15*C15 -> 300 | E15: =Hypothèses!$B$8 -> 600 | F15: =B15*E15 -> 900
A16: Étalonnage | B16: 1 | C16: =Hypothèses!$B$12 -> 200 | D16: =B16*C16 -> 200 | E16: =Hypothèses!$B$9 -> 480 | F16: =B16*E16 -> 480
A17: Mix | B17: 1 | C17: =Hypothèses!$B$12 -> 200 | D17: =B17*C17 -> 200 | E17: =Hypothèses!$B$10 -> 480 | F17: =B17*E17 -> 480
A18: Sous-titrage | B18: 0.5 | C18: =Hypothèses!$B$12 -> 200 | D18: =B18*C18 -> 100 | E18: =Hypothèses!$B$7 -> 500 | F18: =B18*E18 -> 250
A19: Retours ANFA — 2 allers-retours inclus | B19: 1 | C19: =Hypothèses!$B$12 -> 200 | D19: =B19*C19 -> 200 | E19: =Hypothèses!$B$7 -> 500 | F19: =B19*E19 -> 500
A20: FORMAT INNOVANT — déclinaisons courtes issues du long
A21: Déclinaisons courtes (3 extraits de 60 s, ½ j chacune) | B21: 1.5 | C21: =Hypothèses!$B$12 -> 200 | D21: =B21*C21 -> 300 | E21: =Hypothèses!$B$7 -> 500 | F21: =B21*E21 -> 750
A22: Stockage rushes | B22: 1 | C22: =Hypothèses!$B$16 -> 50 | D22: =B22*C22 -> 50 | E22: =Hypothèses!$B$16 -> 50 | F22: =B22*E22 -> 50
A23: Sous-total production | D23: =SUM(D5:D22) -> 4050 | F23: =SUM(F5:F22) -> 10485
A24: Pilotage | C24: =Hypothèses!$B$17 -> 0.15 | D24: =D23*C24 -> 607.5 | E24: =Hypothèses!$B$17 -> 0.15 | F24: =F23*E24 -> 1572.75
A25: Assurance production | C25: =Hypothèses!$B$18 -> 0.03 | D25: =D23*C25 -> 121.5 | E25: =Hypothèses!$B$18 -> 0.03 | F25: =F23*E25 -> 314.55
A26: Provision imprévus | C26: =Hypothèses!$B$19 -> 0.05 | D26: =D23*C26 -> 202.5 | E26: =Hypothèses!$B$19 -> 0.05 | F26: =F23*E26 -> 524.25
A27: COÛT DE REVIENT PRODUCTION (HT) — par vidéo, hors logistique | D27: =D23+D24+D25+D26 -> 4981.5 | F27: =F23+F24+F25+F26 -> 12896.55
A29: Les 3 déclinaisons courtes tirées de chaque long répondent à l'appel aux « formats innovants » du CDC et nourrissent la diffusion (6 courts de plus par an pour un coût marginal). Ligne à passer à 0 si les OPS ne la retiennent pas.

Sheet Logistique vague
A1: LOGISTIQUE D'UNE VAGUE DE TOURNAGE EN RÉGION (2 courts + 1 long) — identique dans les deux scénarios
A2: Poste | B2: Calcul | C2: Quantité | D2: Coût
A3: Transport A/R Paris–région | B3: personnes × A/R | C3: =Hypothèses!$B$22 -> 2 | D3: =C3*Hypothèses!$B$25 -> 300
A4: Hôtel | B4: personnes × nuits | C4: =Hypothèses!$B$22*Hypothèses!$B$24 -> 6 | D4: =C4*Hypothèses!$B$26 -> 570
A5: Per diem repas | B5: personnes × (jours de tournage + 1) | C5: =Hypothèses!$B$22*(Hypothèses!$B$23+1) -> 8 | D5: =C5*Hypothèses!$B$27 -> 320
A6: Location véhicule sur place | B6: jours de tournage | C6: =Hypothèses!$B$23 -> 3 | D6: =C6*Hypothèses!$B$28 -> 210
A7: Sous-total logistique | D7: =SUM(D3:D6) -> 1400
A8: Provision imprévus | C8: =Hypothèses!$B$19 -> 0.05 | D8: =D7*C8 -> 70
A9: COÛT LOGISTIQUE PAR VAGUE (HT) | D9: =D7+D8 -> 1470
A11: Un seul déplacement sert trois vidéos : c'est l'argument RSE (moins de trajets, empreinte carbone réduite) et la condition pour tenir le budget. Tournages mutualisés acceptés par l'ANFA (réponse du 28/10).

Sheet Synthèse
A1: SYNTHÈSE — scénario annuel 2027, comparé au budget maximum du Lot 1
A2: Poste | B2: Quantité | D2: Total A (interne) | E2: Total B (freelances)
A3: COÛT UNITAIRE COMPLET PAR FORMAT (production + part de logistique) — base des prix unitaires pour les bons de commande
A4: Format | C4: Coût unitaire A | E4: Coût unitaire B
A5: Format court (60–120 s) | C5: ='Format court'!$D$23+'Logistique vague'!$D$9*Hypothèses!$B$33 -> 1659 | E5: ='Format court'!$F$23+'Logistique vague'!$D$9*Hypothèses!$B$33 -> 3491.7
A6: Format long (10–15 min) + 3 déclinaisons courtes | C6: ='Format long'!$D$27+'Logistique vague'!$D$9*Hypothèses!$B$34 -> 5716.5 | E6: ='Format long'!$F$27+'Logistique vague'!$D$9*Hypothèses!$B$34 -> 13631.55
A8: SCÉNARIO ANNUEL MINIMUM (volumes du cahier des charges)
A9: Poste | B9: Quantité | D9: Total A (interne) | E9: Total B (freelances)
A10: Formats courts — production | B10: =Hypothèses!$B$31 -> 4 | D10: =B10*'Format court'!$D$23 -> 5166 | E10: =B10*'Format court'!$F$23 -> 12496.8
A11: Formats longs (avec 3 déclinaisons chacun) — production | B11: =Hypothèses!$B$32 -> 2 | D11: =B11*'Format long'!$D$27 -> 9963 | E11: =B11*'Format long'!$F$27 -> 25793.1
A12: Logistique des vagues de tournage en région | B12: =Hypothèses!$B$30 -> 2 | D12: =B12*'Logistique vague'!$D$9 -> 2940 | E12: =B12*'Logistique vague'!$D$9 -> 2940
A13: COÛT DE REVIENT PRODUCTION ANNUEL (HT) | D13: =SUM(D10:D12) -> 18069 | E13: =SUM(E10:E12) -> 41229.9
A14: Vidéos livrées par an (courts + longs + 3 déclinaisons par long) | B14: =B10+B11*4 -> 12
A15: TVA | D15: =D13*Hypothèses!$B$20 -> 3613.8 | E15: =E13*Hypothèses!$B$20 -> 8245.98
A16: Coût de revient production annuel (TTC) | D16: =D13+D15 -> 21682.8 | E16: =E13+E15 -> 49475.88
A18: COMPARAISON AU BUDGET CLIENT (HT) — 58 k€ = production + diffusion + achats médias + marge
A19: Budget annuel maximum Lot 1 (HT) | D19: =Hypothèses!$B$36 -> 58000 | E19: =Hypothèses!$B$36 -> 58000
A20: Part du budget absorbée par la production (coût de revient) | D20: =D13/D19 -> 0.31153448 | E20: =E13/E19 -> 0.71086034
A21: Reste avant marge : médiatisation + marge OPS | D21: =D19-D13 -> 39931 | E21: =E19-E13 -> 16770.1
A22: Production au prix plancher OPS (coût × repère de marge) | D22: =D13*Hypothèses!$B$37 -> 23489.7 | E22: =E13*Hypothèses!$B$37 -> 53598.87
A23: Reste pour la médiatisation après marge plancher | D23: =D19-D22 -> 34510.3 | E23: =E19-E22 -> 4401.13
A25: BASCULE A → B (si la cellule n'a pas la bande passante)
A26: Surcoût de revient si la production bascule en freelances (HT) | E26: =E13-D13 -> 23160.9
A27: Surcoût en % du scénario A | E27: =IF(D13=0,0,(E13-D13)/D13) -> 1.2818031
A29: ⚠️ Le coût A est de la masse salariale déjà payée (taux 200 €/j), pas une dépense de trésorerie : il mesure la charge de la cellule, pas un achat. Matériel interne non valorisé (hors référentiel).
A30: ⚠️ La marge et la répartition médiatisation / marge relèvent des OPS. Le repère ×1,3 n'est affiché que pour visualiser ce qu'il reste à la diffusion ; ce n'est pas une décision.
A31: ⚠️ Achats médias : la publicité ciblée vers les mineurs est très restreinte sur les grandes plateformes européennes ; la diffusion organique sur nos canaux reste l'atout principal (à chiffrer par les RS).

Sheet Calendrier 2027
A1: CALENDRIER 2027 — hypothèse de production en deux vagues (sous réserve de notification en janvier)
A2: Période | B2: Étape | C2: Vidéos concernées | D2: Coût de revient A | E2: Coût de revient B
A3: Janvier | B3: Réunion de lancement ANFA : calage campagnes, sujets, circuit de validation, indicateurs | C3: —
A4: Février | B4: Préprod vague 1 : choix des sites avec l'ANFA, brief intervenants, autorisations | C4: —
A5: Fin février – mars | B5: Tournage vague 1 | C5: 1 court métier + 1 court formation + long n°1 | D5: =2*'Format court'!$D$23+'Format long'!$D$27+'Logistique vague'!$D$9 -> 9034.5 | E5: =2*'Format court'!$F$23+'Format long'!$F$27+'Logistique vague'!$D$9 -> 20614.95
A6: Mars – avril | B6: Post-prod vague 1, validations ANFA, diffusion des courts (choix d'orientation de fin de 3e, portes ouvertes CFA) | C6: —
A7: Avril – mai | B7: Préprod vague 2 | C7: —
A8: Mai | B8: Tournage vague 2 (avant la période du Bac) | C8: 1 court métier + 1 court formation + long n°2 | D8: =2*'Format court'!$D$23+'Format long'!$D$27+'Logistique vague'!$D$9 -> 9034.5 | E8: =2*'Format court'!$F$23+'Format long'!$F$27+'Logistique vague'!$D$9 -> 20614.95
A9: Juin – juillet | B9: Post-prod vague 2 | C9: —
A10: Septembre – octobre | B10: Diffusion de rentrée, déclinaisons, relais prescripteurs | C10: —
A11: Novembre – décembre | B11: Bilan annuel quantitatif et qualitatif (base de la décision de reconduction) | C11: —
A12: TOTAL (doit égaler la Synthèse) | D12: =D5+D8 -> 18069 | E12: =E5+E8 -> 41229.9
A13: Contrôle : écart avec la Synthèse | D13: =D12-Synthèse!$D$13 -> 0 | E13: =E12-Synthèse!$E$13 -> 0
