Workbook

Sheet Hypothèses
A1: LÉGENDE : cellules bleues = valeurs modifiables (inputs) — cellules noires = formules.
A2: SCÉNARIO RESSERRÉ : équipe tournage réduite à 4 postes (Réal/Cadreur/Ingé son/Régie), tournage 1,5j, kit intermédiaire — pour tenir l'enveloppe client. Voir Fiche Approche pour le scénario complet écarté (7 postes, 2j, kit lourd).
A3: Poste | B3: Valeur | C3: Unité | D3: Source
A4: Réalisateur (pub/fiction) | B4: 1200 | C4: €/j | D4: BPU IDFM Grille Coûts Production — SPIAC / Marché pub
A5: Cadreur / JRI (chef opérateur, assure aussi la lumière simple) | B5: 550 | C5: €/j | D5: BPU IDFM Grille Coûts Production — COMETES / Malt
A6: Chef OPS / Ingénieur du son | B6: 500 | C6: €/j | D6: BPU IDFM Grille Coûts Production — COMETES / CCPA
A7: Assistant·e de production (régie) | B7: 300 | C7: €/j | D7: BPU IDFM Grille Coûts Production — COMETES
A8: Monteur·se | B8: 500 | C8: €/j | D8: BPU IDFM Grille Coûts Production — COMETES / Malt
A9: Étalonneur·se | B9: 480 | C9: €/j | D9: BPU IDFM Grille Coûts Production — COMETES / Malt
A10: Mixeur·se | B10: 480 | C10: €/j | D10: BPU IDFM Grille Coûts Production — COMETES / CCPA
A11: Motion designer | B11: 600 | C11: €/j | D11: BPU IDFM Grille Coûts Production — Marché pub / Malt
A12: Storyboarder (freelance) | B12: 400 | C12: €/j | D12: BPU IDFM Grille Coûts Production — Marché pub
A13: Taux interne (supervision / coordination) | B13: 200 | C13: €/j | D13: Référentiel de Coûts Internes Pôle Audiovisuel — validé Direction
A14: Comédien image (hors droits) | B14: 534 | C14: €/j | D14: Cachet minimum tournage "Publicité & contenus de marque" ≈ 534 €/j (grilles syndicales 2025, hors droits de diffusion) — retenu au plancher conventionnel, pas de marge au-dessus
A15: Coefficient intermittent (charges Congés Spectacles) | B15: 0.154 | C15: % | D15: BPU IDFM / Audiens — cotisation employeur 15,4% sur salaire brut
... A25: Location kit lumière 3 points (LED, softbox, pieds) | B25: 200 | C25: €/j | D25: Estimation marché — kit LED 3 points (type Aputure/Godox), indispensable sur les deux scénarios
A26: — SCÉNARIO A : postes et taux additionnels (équipe complète / tarifs standards, non compressés) —
A27: 1er Assistant réalisateur | B27: 450 | C27: €/j | D27: BPU IDFM Grille Coûts Production — COMETES / CCPA
A28: Machiniste | B28: 340 | C28: €/j | D28: BPU IDFM Grille Coûts Production — COMETES / CCPA
A29: Chef électricien | B29: 430 | C29: €/j | D29: BPU IDFM Grille Coûts Production — COMETES / CCPA
A30: Location kit tournage lourd / multicam | B30: 1500 | C30: €/j | D30: BPU IDFM Grille Coûts Production — équipe complète, dispositif lumière/son renforcé
A31: Maquilleuse / Styliste | B31: 400 | C31: €/j | D31: Estimation marché — TJM freelance maquillage/coiffure/stylisme plateau, au-dessus du minimum conventionnel CCPA (155-250 €/j film institutionnel/TV, IDCC 2642)
A32: Fournitures maquillage/coiffure (forfait, hors garde-robe) | B32: 80 | C32: € | D32: Estimation interne — consommables maquillage/coiffure (produits, accessoires) ; garde-robe non chiffrée, puisée dans les vêtements personnels des comédiens

Sheet CYRCE_A
A1: Poste | B1: Jours / Quantité | C1: Taux unitaire | D1: Coût
A2: PRÉ-PRODUCTION
A3: Écriture scénario (interne, direction créative) | B3: 1.5 | C3: =Hypothèses!$B$13 -> 200 | D3: =B3*C3 -> 300
A4: Storyboard (freelance) | B4: 1 | C4: =Hypothèses!$B$12 -> 400 | D4: =B4*C4 -> 400
A5: Repérages Normandie (régie) | B5: 0.5 | C5: =Hypothèses!$B$7 -> 300 | D5: =B5*C5 -> 150
A6: Casting — recherche & coordination (interne) | B6: 1 | C6: =Hypothèses!$B$13 -> 200 | D6: =B6*C6 -> 200
A7: TOURNAGE (2 jours, équipe complète — SCÉNARIO A, 8 postes, kit lourd/multicam)
A8: Réalisateur | B8: 2 | C8: =Hypothèses!$B$4 -> 1200 | D8: =B8*C8 -> 2400
A9: 1er Assistant réalisateur | B9: 2 | C9: =Hypothèses!$B$27 -> 450 | D9: =B9*C9 -> 900
A10: Cadreur / JRI | B10: 2 | C10: =Hypothèses!$B$5 -> 550 | D10: =B10*C10 -> 1100
A11: Chef OPS / Ingénieur du son | B11: 2 | C11: =Hypothèses!$B$6 -> 500 | D11: =B11*C11 -> 1000
A12: Machiniste | B12: 2 | C12: =Hypothèses!$B$28 -> 340 | D12: =B12*C12 -> 680
A13: Chef électricien | B13: 2 | C13: =Hypothèses!$B$29 -> 430 | D13: =B13*C13 -> 860
A14: Régie / assistant production | B14: 2 | C14: =Hypothèses!$B$7 -> 300 | D14: =B14*C14 -> 600
A15: Maquilleuse / Styliste | B15: 2 | C15: =Hypothèses!$B$31 -> 400 | D15: =B15*C15 -> 800
A16: Supervision interne (présence tournage) | B16: 1 | C16: =Hypothèses!$B$13 -> 200 | D16: =B16*C16 -> 200
A17: Comédiens — jours-comédien (2 comédiens × 2j) | B17: 4 | C17: =Hypothèses!$B$14 -> 534 | D17: =B17*C17 -> 2136
A18: Comédiens — charges Congés Spectacles | C18: =Hypothèses!$B$15 -> 0.154 | D18: =D17*C18 -> 328.944
A19: Transport aller-retour équipe (8 pers.) | B19: 8 | C19: =Hypothèses!$B$17 -> 90 | D19: =B19*C19 -> 720
A20: Hébergement — nuitées équipe (8 pers. × 2 nuits) | B20: 16 | C20: =Hypothèses!$B$23 -> 95 | D20: =B20*C20 -> 1520
A21: Repas — per diem équipe (8 pers. × 3 jours) | B21: 24 | C21: =Hypothèses!$B$24 -> 40 | D21: =B21*C21 -> 960
A22: Location kit tournage lourd / multicam | B22: 2 | C22: =Hypothèses!$B$30 -> 1500 | D22: =B22*C22 -> 3000
A23: Location kit lumière 3 points (LED, softbox, pieds) | B23: 2 | C23: =Hypothèses!$B$25 -> 200 | D23: =B23*C23 -> 400
A24: Fournitures maquillage/coiffure (forfait) | B24: 1 | C24: =Hypothèses!$B$32 -> 80 | D24: =B24*C24 -> 80
A25: POST-PRODUCTION
A26: Montage | B26: 3 | C26: =Hypothèses!$B$8 -> 500 | D26: =B26*C26 -> 1500
A27: Étalonnage | B27: 0.5 | C27: =Hypothèses!$B$9 -> 480 | D27: =B27*C27 -> 240
A28: Mixage son | B28: 0.5 | C28: =Hypothèses!$B$10 -> 480 | D28: =B28*C28 -> 240
A29: Motion design / habillage | B29: 1 | C29: =Hypothèses!$B$11 -> 600 | D29: =B29*C29 -> 600
A30: Sous-titrage + déclinaisons RS (30s + vertical) | B30: 1 | C30: =Hypothèses!$B$8 -> 500 | D30: =B30*C30 -> 500
A31: SOUS-TOTAL PRODUCTION | D31: =D3+D4+D5+D6+D8+D9+D10+D11+D12+D13+D14+D15+D16+D17+D18+D19+D20+D21+D22+D23+D24+D26+D27+D28+D29+D30 -> 21814.944
A32: Pilotage | C32: =Hypothèses!$B$18 -> 0.15 | D32: =D31*Hypothèses!$B$18 -> 3272.2416
A33: Assurance production | C33: =Hypothèses!$B$19 -> 0.03 | D33: =D31*Hypothèses!$B$19 -> 654.44832
A34: Provision imprévus | C34: =Hypothèses!$B$20 -> 0.05 | D34: =D31*Hypothèses!$B$20 -> 1090.7472
A35: TOTAL coût de revient (HT) | D35: =D31+D32+D33+D34 -> 26832.381

Sheet CYRCE_B
A1: Poste | B1: Jours / Quantité | C1: Taux unitaire | D1: Coût
A2: PRÉ-PRODUCTION
A3: Écriture scénario (interne, direction créative) | B3: 1.5 | C3: =Hypothèses!$B$13 -> 200 | D3: =B3*C3 -> 300
A4: Storyboard (freelance) | B4: 1 | C4: =Hypothèses!$B$12 -> 400 | D4: =B4*C4 -> 400
A5: Repérages Normandie (régie) | B5: 0.5 | C5: =Hypothèses!$B$7 -> 300 | D5: =B5*C5 -> 150
A6: Casting — recherche & coordination (interne) | B6: 1 | C6: =Hypothèses!$B$13 -> 200 | D6: =B6*C6 -> 200
A7: TOURNAGE (1,5 jour, équipe resserrée — SCÉNARIO B, contrainte budget AO)
A8: Réalisateur | B8: 1.5 | C8: =Hypothèses!$B$4 -> 1200 | D8: =B8*C8 -> 1800
A9: Cadreur / JRI | B9: 1.5 | C9: =Hypothèses!$B$5 -> 550 | D9: =B9*C9 -> 825
A10: Chef OPS / Ingénieur du son | B10: 1.5 | C10: =Hypothèses!$B$6 -> 500 | D10: =B10*C10 -> 750
A11: Régie / assistant production | B11: 1.5 | C11: =Hypothèses!$B$7 -> 300 | D11: =B11*C11 -> 450
A12: Supervision interne (présence tournage) | B12: 0.5 | C12: =Hypothèses!$B$13 -> 200 | D12: =B12*C12 -> 100
A13: Comédiens — jours-comédien (2 comédiens × 1.5j) | B13: 3 | C13: =Hypothèses!$B$14 -> 534 | D13: =B13*C13 -> 1602
A14: Comédiens — charges Congés Spectacles | C14: =Hypothèses!$B$15 -> 0.154 | D14: =D13*C14 -> 246.708
A15: Transport aller-retour équipe (4 pers.) | B15: 4 | C15: =Hypothèses!$B$17 -> 90 | D15: =B15*C15 -> 360
A16: Hébergement — nuitées équipe (4 pers. × 2 nuits) | B16: 8 | C16: =Hypothèses!$B$23 -> 95 | D16: =B16*C16 -> 760
A17: Repas — per diem équipe (4 pers. × 3 jours) | B17: 12 | C17: =Hypothèses!$B$24 -> 40 | D17: =B17*C17 -> 480
A18: Location kit tournage intermédiaire | B18: 1.5 | C18: =Hypothèses!$B$16 -> 700 | D18: =B18*C18 -> 1050
A19: Location kit lumière 3 points (LED, softbox, pieds) | B19: 1.5 | C19: =Hypothèses!$B$25 -> 200 | D19: =B19*C19 -> 300
A20: POST-PRODUCTION
A21: Montage | B21: 3 | C21: =Hypothèses!$B$8 -> 500 | D21: =B21*C21 -> 1500
A22: Étalonnage | B22: 0.5 | C22: =Hypothèses!$B$9 -> 480 | D22: =B22*C22 -> 240
A23: Mixage son | B23: 0.5 | C23: =Hypothèses!$B$10 -> 480 | D23: =B23*C23 -> 240
A24: Motion design / habillage | B24: 1 | C24: =Hypothèses!$B$11 -> 600 | D24: =B24*C24 -> 600
A25: Sous-titrage + déclinaisons RS (30s + vertical) | B25: 1 | C25: =Hypothèses!$B$8 -> 500 | D25: =B25*C25 -> 500
A26: SOUS-TOTAL PRODUCTION | D26: =D3+D4+D5+D6+D8+D9+D10+D11+D12+D13+D14+D15+D16+D17+D18+D19+D21+D22+D23+D24+D25 -> 12853.708
A27: Pilotage | C27: =Hypothèses!$B$18 -> 0.15 | D27: =D26*Hypothèses!$B$18 -> 1928.0562
A28: Assurance production | C28: =Hypothèses!$B$19 -> 0.03 | D28: =D26*Hypothèses!$B$19 -> 385.61124
A29: Provision imprévus | C29: =Hypothèses!$B$20 -> 0.05 | D29: =D26*Hypothèses!$B$20 -> 642.6854
A30: TOTAL coût de revient (HT) | D30: =D26+D27+D28+D29 -> 15810.061

Sheet BIOT2_A
A1: Poste | B1: Jours / Quantité | C1: Taux unitaire | D1: Coût
A2: PRÉ-PRODUCTION
A3: Écriture scénario (interne, direction créative) | B3: 1.5 | C3: =Hypothèses!$B$13 -> 200 | D3: =B3*C3 -> 300
A4: Storyboard (freelance) | B4: 1 | C4: =Hypothèses!$B$12 -> 400 | D4: =B4*C4 -> 400
A5: Repérages Normandie (régie) | B5: 0.5 | C5: =Hypothèses!$B$7 -> 300 | D5: =B5*C5 -> 150
A6: Casting — recherche & coordination (interne) | B6: 1 | C6: =Hypothèses!$B$13 -> 200 | D6: =B6*C6 -> 200
A7: TOURNAGE (2 jours, équipe complète — SCÉNARIO A, 8 postes, kit lourd/multicam)
A8: Réalisateur | B8: 2 | C8: =Hypothèses!$B$4 -> 1200 | D8: =B8*C8 -> 2400
A9: 1er Assistant réalisateur | B9: 2 | C9: =Hypothèses!$B$27 -> 450 | D9: =B9*C9 -> 900
A10: Cadreur / JRI | B10: 2 | C10: =Hypothèses!$B$5 -> 550 | D10: =B10*C10 -> 1100
A11: Chef OPS / Ingénieur du son | B11: 2 | C11: =Hypothèses!$B$6 -> 500 | D11: =B11*C11 -> 1000
A12: Machiniste | B12: 2 | C12: =Hypothèses!$B$28 -> 340 | D12: =B12*C12 -> 680
A13: Chef électricien | B13: 2 | C13: =Hypothèses!$B$29 -> 430 | D13: =B13*C13 -> 860
A14: Régie / assistant production | B14: 2 | C14: =Hypothèses!$B$7 -> 300 | D14: =B14*C14 -> 600
A15: Maquilleuse / Styliste | B15: 2 | C15: =Hypothèses!$B$31 -> 400 | D15: =B15*C15 -> 800
A16: Supervision interne (présence tournage) | B16: 1 | C16: =Hypothèses!$B$13 -> 200 | D16: =B16*C16 -> 200
A17: Comédiens — jours-comédien (2 comédiens × 2j) | B17: 4 | C17: =Hypothèses!$B$14 -> 534 | D17: =B17*C17 -> 2136
A18: Comédiens — charges Congés Spectacles | C18: =Hypothèses!$B$15 -> 0.154 | D18: =D17*C18 -> 328.944
A19: Transport aller-retour équipe (8 pers.) | B19: 8 | C19: =Hypothèses!$B$17 -> 90 | D19: =B19*C19 -> 720
A20: Hébergement — nuitées équipe (8 pers. × 2 nuits) | B20: 16 | C20: =Hypothèses!$B$23 -> 95 | D20: =B20*C20 -> 1520
A21: Repas — per diem équipe (8 pers. × 3 jours) | B21: 24 | C21: =Hypothèses!$B$24 -> 40 | D21: =B21*C21 -> 960
A22: Location kit tournage lourd / multicam | B22: 2 | C22: =Hypothèses!$B$30 -> 1500 | D22: =B22*C22 -> 3000
A23: Location kit lumière 3 points (LED, softbox, pieds) | B23: 2 | C23: =Hypothèses!$B$25 -> 200 | D23: =B23*C23 -> 400
A24: Fournitures maquillage/coiffure (forfait) | B24: 1 | C24: =Hypothèses!$B$32 -> 80 | D24: =B24*C24 -> 80
A25: POST-PRODUCTION
A26: Montage | B26: 3 | C26: =Hypothèses!$B$8 -> 500 | D26: =B26*C26 -> 1500
A27: Étalonnage | B27: 0.5 | C27: =Hypothèses!$B$9 -> 480 | D27: =B27*C27 -> 240
A28: Mixage son | B28: 0.5 | C28: =Hypothèses!$B$10 -> 480 | D28: =B28*C28 -> 240
A29: Motion design / habillage | B29: 1 | C29: =Hypothèses!$B$11 -> 600 | D29: =B29*C29 -> 600
A30: Sous-titrage + déclinaisons RS (30s + vertical) | B30: 1 | C30: =Hypothèses!$B$8 -> 500 | D30: =B30*C30 -> 500
A31: SOUS-TOTAL PRODUCTION | D31: =D3+D4+D5+D6+D8+D9+D10+D11+D12+D13+D14+D15+D16+D17+D18+D19+D20+D21+D22+D23+D24+D26+D27+D28+D29+D30 -> 21814.944
A32: Pilotage | C32: =Hypothèses!$B$18 -> 0.15 | D32: =D31*Hypothèses!$B$18 -> 3272.2416
A33: Assurance production | C33: =Hypothèses!$B$19 -> 0.03 | D33: =D31*Hypothèses!$B$19 -> 654.44832
A34: Provision imprévus | C34: =Hypothèses!$B$20 -> 0.05 | D34: =D31*Hypothèses!$B$20 -> 1090.7472
A35: TOTAL coût de revient (HT) | D35: =D31+D32+D33+D34 -> 26832.381

Sheet BIOT2_B
A1: Poste | B1: Jours / Quantité | C1: Taux unitaire | D1: Coût
A2: PRÉ-PRODUCTION
A3: Écriture scénario (interne, direction créative) | B3: 1.5 | C3: =Hypothèses!$B$13 -> 200 | D3: =B3*C3 -> 300
A4: Storyboard (freelance) | B4: 1 | C4: =Hypothèses!$B$12 -> 400 | D4: =B4*C4 -> 400
A5: Repérages Normandie (régie) | B5: 0.5 | C5: =Hypothèses!$B$7 -> 300 | D5: =B5*C5 -> 150
A6: Casting — recherche & coordination (interne) | B6: 1 | C6: =Hypothèses!$B$13 -> 200 | D6: =B6*C6 -> 200
A7: TOURNAGE (1,5 jour, équipe resserrée — SCÉNARIO B, contrainte budget AO)
A8: Réalisateur | B8: 1.5 | C8: =Hypothèses!$B$4 -> 1200 | D8: =B8*C8 -> 1800
A9: Cadreur / JRI | B9: 1.5 | C9: =Hypothèses!$B$5 -> 550 | D9: =B9*C9 -> 825
A10: Chef OPS / Ingénieur du son | B10: 1.5 | C10: =Hypothèses!$B$6 -> 500 | D10: =B10*C10 -> 750
A11: Régie / assistant production | B11: 1.5 | C11: =Hypothèses!$B$7 -> 300 | D11: =B11*C11 -> 450
A12: Supervision interne (présence tournage) | B12: 0.5 | C12: =Hypothèses!$B$13 -> 200 | D12: =B12*C12 -> 100
A13: Comédiens — jours-comédien (2 comédiens × 1.5j) | B13: 3 | C13: =Hypothèses!$B$14 -> 534 | D13: =B13*C13 -> 1602
A14: Comédiens — charges Congés Spectacles | C14: =Hypothèses!$B$15 -> 0.154 | D14: =D13*C14 -> 246.708
A15: Transport aller-retour équipe (4 pers.) | B15: 4 | C15: =Hypothèses!$B$17 -> 90 | D15: =B15*C15 -> 360
A16: Hébergement — nuitées équipe (4 pers. × 2 nuits) | B16: 8 | C16: =Hypothèses!$B$23 -> 95 | D16: =B16*C16 -> 760
A17: Repas — per diem équipe (4 pers. × 3 jours) | B17: 12 | C17: =Hypothèses!$B$24 -> 40 | D17: =B17*C17 -> 480
A18: Location kit tournage intermédiaire | B18: 1.5 | C18: =Hypothèses!$B$16 -> 700 | D18: =B18*C18 -> 1050
A19: Location kit lumière 3 points (LED, softbox, pieds) | B19: 1.5 | C19: =Hypothèses!$B$25 -> 200 | D19: =B19*C19 -> 300
A20: POST-PRODUCTION
A21: Montage | B21: 3 | C21: =Hypothèses!$B$8 -> 500 | D21: =B21*C21 -> 1500
A22: Étalonnage | B22: 0.5 | C22: =Hypothèses!$B$9 -> 480 | D22: =B22*C22 -> 240
A23: Mixage son | B23: 0.5 | C23: =Hypothèses!$B$10 -> 480 | D23: =B23*C23 -> 240
A24: Motion design / habillage | B24: 1 | C24: =Hypothèses!$B$11 -> 600 | D24: =B24*C24 -> 600
A25: Sous-titrage + déclinaisons RS (30s + vertical) | B25: 1 | C25: =Hypothèses!$B$8 -> 500 | D25: =B25*C25 -> 500
A26: SOUS-TOTAL PRODUCTION | D26: =D3+D4+D5+D6+D8+D9+D10+D11+D12+D13+D14+D15+D16+D17+D18+D19+D21+D22+D23+D24+D25 -> 12853.708
A27: Pilotage | C27: =Hypothèses!$B$18 -> 0.15 | D27: =D26*Hypothèses!$B$18 -> 1928.0562
A28: Assurance production | C28: =Hypothèses!$B$19 -> 0.03 | D28: =D26*Hypothèses!$B$19 -> 385.61124
A29: Provision imprévus | C29: =Hypothèses!$B$20 -> 0.05 | D29: =D26*Hypothèses!$B$20 -> 642.6854
A30: TOTAL coût de revient (HT) | D30: =D26+D27+D28+D29 -> 15810.061

Sheet Synthèse
A1: Poste | B1: Montant
A2: SCÉNARIO A — Tarifs internes (équipe complète, sans compression)
A3: Total coût de revient CYRCE (HT) | B3: =CYRCE_A!D35 -> 26832.381
A4: Total coût de revient BIOT2 (HT) | B4: =BIOT2_A!D35 -> 26832.381
A5: TOTAL Scénario A — coût de revient global (HT) | B5: =B3+B4 -> 53664.762
A6: TVA | B6: =B5*Hypothèses!$B$21 -> 10732.952
A7: TOTAL Scénario A (TTC) | B7: =B5+B6 -> 64397.715
A9: SCÉNARIO B — Contrainte budget AO (resserré)
A10: Total coût de revient CYRCE (HT) | B10: =CYRCE_B!D30 -> 15810.061
A11: Total coût de revient BIOT2 (HT) | B11: =BIOT2_B!D30 -> 15810.061
A12: TOTAL Scénario B — coût de revient global (HT) | B12: =B10+B11 -> 31620.122
A13: TVA | B13: =B12*Hypothèses!$B$21 -> 6324.0243
A14: TOTAL Scénario B (TTC) | B14: =B12+B13 -> 37944.146
A16: COMPARATIF AU BUDGET CLIENT
A17: Enveloppe budgétaire client (TTC) | B17: =Hypothèses!$B$22 -> 40000
A18: Marge disponible Scénario B vs enveloppe (avant marge commerciale OPS) | B18: =B17-B14 -> 2055.854
A20: ÉCART A → B — RISQUE / MANQUE À GAGNER SI SCÉNARIO B RETENU
A21: Écart HT (coût réel équipe complète − coût scénario contraint) | B21: =B5-B12 -> 22044.641
A22: Écart TTC | B22: =B7-B14 -> 26453.569
A23: Écart en % du coût réel Scénario A (HT) | B23: =B21/B5 -> 0.41078428
